rasaio/__init__.py
rasaio/integrations/__init__.py
rasaio/integrations/constants.py
rasaio/integrations/salesforce/__init__.py
rasaio/integrations/salesforce/salesforce.py
rasaio/integrations/test/__init__.py
rasaio/integrations/test/test_salesforce.py
rasaio/integrations/utilties/__init__.py
rasaio/integrations/utilties/helper.py
rasaio_integrations-1.0.15.dist-info/LICENSE.txt
rasaio_integrations-1.0.15.dist-info/METADATA
rasaio_integrations-1.0.15.dist-info/WHEEL
rasaio_integrations-1.0.15.dist-info/top_level.txt
rasaio_integrations-1.0.15.dist-info/zip-safe
rasaio_integrations-1.0.15.dist-info/RECORD
